{
  "format_id": "amvision.custom-node-catalog.v1",
  "payload_contracts": [
    {
      "format_id": "amvision.workflow-payload-contract.v1",
      "payload_type_id": "contours.v1",
      "display_name": "Contour Result",
      "transport_kind": "inline-json",
      "json_schema": {
        "type": "object",
        "properties": {
          "source_image": {
            "type": "object",
            "properties": {
              "transport_kind": {
                "type": "string",
                "enum": [
                  "memory",
                  "storage",
                  "buffer",
                  "frame"
                ]
              },
              "object_key": {
                "type": "string"
              },
              "image_handle": {
                "type": "string"
              },
              "buffer_ref": {
                "type": "object"
              },
              "frame_ref": {
                "type": "object"
              },
              "width": {
                "type": "integer"
              },
              "height": {
                "type": "integer"
              },
              "media_type": {
                "type": "string"
              }
            },
            "required": [
              "transport_kind",
              "media_type"
            ],
            "oneOf": [
              {
                "properties": {
                  "transport_kind": {
                    "const": "storage"
                  }
                },
                "required": [
                  "object_key"
                ]
              },
              {
                "properties": {
                  "transport_kind": {
                    "const": "memory"
                  }
                },
                "required": [
                  "image_handle"
                ]
              },
              {
                "properties": {
                  "transport_kind": {
                    "const": "buffer"
                  }
                },
                "required": [
                  "buffer_ref"
                ]
              },
              {
                "properties": {
                  "transport_kind": {
                    "const": "frame"
                  }
                },
                "required": [
                  "frame_ref"
                ]
              }
            ]
          },
          "source_object_key": {
            "type": "string"
          },
          "count": {
            "type": "integer"
          },
          "items": {
            "type": "array",
            "items": {
              "type": "object",
              "properties": {
                "contour_index": {
                  "type": "integer"
                },
                "point_count": {
                  "type": "integer"
                },
                "bbox_xyxy": {
                  "type": "array",
                  "items": {
                    "type": "integer"
                  },
                  "minItems": 4,
                  "maxItems": 4
                },
                "points": {
                  "type": "array",
                  "items": {
                    "type": "array",
                    "items": {
                      "type": "integer"
                    },
                    "minItems": 2,
                    "maxItems": 2
                  }
                }
              },
              "required": [
                "contour_index",
                "bbox_xyxy",
                "points"
              ]
            }
          }
        },
        "required": [
          "items"
        ]
      },
      "artifact_kinds": [],
      "metadata": {}
    },
    {
      "format_id": "amvision.workflow-payload-contract.v1",
      "payload_type_id": "measurements.v1",
      "display_name": "Measurement Result",
      "transport_kind": "inline-json",
      "json_schema": {
        "type": "object",
        "properties": {
          "source_image": {
            "type": "object",
            "properties": {
              "transport_kind": {
                "type": "string",
                "enum": [
                  "memory",
                  "storage",
                  "buffer",
                  "frame"
                ]
              },
              "object_key": {
                "type": "string"
              },
              "image_handle": {
                "type": "string"
              },
              "buffer_ref": {
                "type": "object"
              },
              "frame_ref": {
                "type": "object"
              },
              "width": {
                "type": "integer"
              },
              "height": {
                "type": "integer"
              },
              "media_type": {
                "type": "string"
              }
            },
            "required": [
              "transport_kind",
              "media_type"
            ],
            "oneOf": [
              {
                "properties": {
                  "transport_kind": {
                    "const": "storage"
                  }
                },
                "required": [
                  "object_key"
                ]
              },
              {
                "properties": {
                  "transport_kind": {
                    "const": "memory"
                  }
                },
                "required": [
                  "image_handle"
                ]
              },
              {
                "properties": {
                  "transport_kind": {
                    "const": "buffer"
                  }
                },
                "required": [
                  "buffer_ref"
                ]
              },
              {
                "properties": {
                  "transport_kind": {
                    "const": "frame"
                  }
                },
                "required": [
                  "frame_ref"
                ]
              }
            ]
          },
          "source_object_key": {
            "type": "string"
          },
          "count": {
            "type": "integer"
          },
          "summary": {
            "type": "object",
            "properties": {
              "total_area": {
                "type": "number"
              },
              "mean_area": {
                "type": "number"
              },
              "max_area": {
                "type": "number"
              },
              "min_area": {
                "type": "number"
              }
            }
          },
          "items": {
            "type": "array",
            "items": {
              "type": "object",
              "properties": {
                "contour_index": {
                  "type": "integer"
                },
                "point_count": {
                  "type": "integer"
                },
                "bbox_xyxy": {
                  "type": "array",
                  "items": {
                    "type": "integer"
                  },
                  "minItems": 4,
                  "maxItems": 4
                },
                "width": {
                  "type": "integer"
                },
                "height": {
                  "type": "integer"
                },
                "area": {
                  "type": "number"
                },
                "perimeter": {
                  "type": "number"
                },
                "center_xy": {
                  "type": "array",
                  "items": {
                    "type": "number"
                  },
                  "minItems": 2,
                  "maxItems": 2
                },
                "aspect_ratio": {
                  "type": "number"
                }
              },
              "required": [
                "contour_index",
                "bbox_xyxy",
                "area",
                "perimeter"
              ]
            }
          }
        },
        "required": [
          "items"
        ]
      },
      "artifact_kinds": [],
      "metadata": {}
    },
    {
      "format_id": "amvision.workflow-payload-contract.v1",
      "payload_type_id": "rotated-rects.v1",
      "display_name": "Rotated Rect Result",
      "transport_kind": "inline-json",
      "json_schema": {
        "type": "object",
        "properties": {
          "source_image": {
            "type": "object",
            "properties": {
              "transport_kind": {
                "type": "string",
                "enum": [
                  "memory",
                  "storage",
                  "buffer",
                  "frame"
                ]
              },
              "object_key": {
                "type": "string"
              },
              "image_handle": {
                "type": "string"
              },
              "buffer_ref": {
                "type": "object"
              },
              "frame_ref": {
                "type": "object"
              },
              "width": {
                "type": "integer"
              },
              "height": {
                "type": "integer"
              },
              "media_type": {
                "type": "string"
              }
            },
            "required": [
              "transport_kind",
              "media_type"
            ],
            "oneOf": [
              {
                "properties": {
                  "transport_kind": {
                    "const": "storage"
                  }
                },
                "required": [
                  "object_key"
                ]
              },
              {
                "properties": {
                  "transport_kind": {
                    "const": "memory"
                  }
                },
                "required": [
                  "image_handle"
                ]
              },
              {
                "properties": {
                  "transport_kind": {
                    "const": "buffer"
                  }
                },
                "required": [
                  "buffer_ref"
                ]
              },
              {
                "properties": {
                  "transport_kind": {
                    "const": "frame"
                  }
                },
                "required": [
                  "frame_ref"
                ]
              }
            ]
          },
          "source_object_key": {
            "type": "string"
          },
          "count": {
            "type": "integer"
          },
          "items": {
            "type": "array",
            "items": {
              "type": "object",
              "properties": {
                "contour_index": {
                  "type": "integer"
                },
                "point_count": {
                  "type": "integer"
                },
                "center_xy": {
                  "type": "array",
                  "items": {
                    "type": "number"
                  },
                  "minItems": 2,
                  "maxItems": 2
                },
                "size_wh": {
                  "type": "array",
                  "items": {
                    "type": "number"
                  },
                  "minItems": 2,
                  "maxItems": 2
                },
                "width": {
                  "type": "number"
                },
                "height": {
                  "type": "number"
                },
                "long_side": {
                  "type": "number"
                },
                "short_side": {
                  "type": "number"
                },
                "angle_deg": {
                  "type": "number"
                },
                "bbox_xyxy": {
                  "type": "array",
                  "items": {
                    "type": "number"
                  },
                  "minItems": 4,
                  "maxItems": 4
                },
                "box_points": {
                  "type": "array",
                  "items": {
                    "type": "array",
                    "items": {
                      "type": "number"
                    },
                    "minItems": 2,
                    "maxItems": 2
                  },
                  "minItems": 4,
                  "maxItems": 4
                },
                "contour_area": {
                  "type": "number"
                },
                "rect_area": {
                  "type": "number"
                },
                "fill_ratio": {
                  "type": "number"
                }
              },
              "required": [
                "contour_index",
                "center_xy",
                "size_wh",
                "long_side",
                "short_side",
                "angle_deg",
                "box_points",
                "contour_area",
                "rect_area"
              ]
            }
          }
        },
        "required": [
          "items"
        ]
      },
      "artifact_kinds": [],
      "metadata": {}
    }
  ],
  "node_definitions": [
    {
      "format_id": "amvision.node-definition.v1",
      "node_type_id": "custom.opencv.absdiff-threshold",
      "display_name": "Absdiff Threshold",
      "category": "opencv.filter",
      "description": "把差分图通过阈值化收成前景变化区域二值图。",
      "implementation_kind": "custom-node",
      "runtime_kind": "python-callable",
      "input_ports": [
        {
          "name": "image",
          "display_name": "Image",
          "payload_type_id": "image-ref.v1",
          "description": "",
          "required": true,
          "multiple": false,
          "metadata": {}
        }
      ],
      "output_ports": [
        {
          "name": "image",
          "display_name": "Image",
          "payload_type_id": "image-ref.v1",
          "description": "",
          "required": true,
          "multiple": false,
          "metadata": {}
        },
        {
          "name": "summary",
          "display_name": "Summary",
          "payload_type_id": "value.v1",
          "description": "",
          "required": true,
          "multiple": false,
          "metadata": {}
        }
      ],
      "parameter_schema": {
        "type": "object",
        "properties": {
          "threshold": {
            "type": "integer",
            "minimum": 0,
            "maximum": 255
          },
          "max_value": {
            "type": "integer",
            "minimum": 0,
            "maximum": 255
          },
          "threshold_type": {
            "type": "string",
            "enum": [
              "binary",
              "binary-inv"
            ]
          },
          "output_object_key": {
            "type": "string"
          }
        }
      },
      "parameter_ui_schema": null,
      "capability_tags": [
        "opencv.absdiff-threshold",
        "vision.filter",
        "vision.diff"
      ],
      "runtime_requirements": {
        "python_packages": [
          "opencv-python",
          "numpy"
        ]
      },
      "node_pack_id": "opencv.basic-nodes",
      "node_pack_version": "0.1.0",
      "metadata": {}
    },
    {
      "format_id": "amvision.node-definition.v1",
      "node_type_id": "custom.opencv.adaptive-threshold",
      "display_name": "Adaptive Threshold",
      "category": "opencv.filter",
      "description": "对输入灰度图执行 adaptive threshold，适合光照不均或背景变化明显的二值化场景。",
      "implementation_kind": "custom-node",
      "runtime_kind": "python-callable",
      "input_ports": [
        {
          "name": "image",
          "display_name": "Image",
          "payload_type_id": "image-ref.v1",
          "description": "",
          "required": true,
          "multiple": false,
          "metadata": {}
        }
      ],
      "output_ports": [
        {
          "name": "image",
          "display_name": "Image",
          "payload_type_id": "image-ref.v1",
          "description": "",
          "required": true,
          "multiple": false,
          "metadata": {}
        }
      ],
      "parameter_schema": {
        "type": "object",
        "properties": {
          "max_value": {
            "type": "number",
            "minimum": 0,
            "maximum": 255
          },
          "adaptive_method": {
            "type": "string",
            "enum": [
              "mean",
              "gaussian"
            ]
          },
          "threshold_type": {
            "type": "string",
            "enum": [
              "binary",
              "binary-inv"
            ]
          },
          "block_size": {
            "type": "integer",
            "minimum": 3
          },
          "c_value": {
            "type": "number"
          },
          "output_object_key": {
            "type": "string"
          }
        }
      },
      "parameter_ui_schema": null,
      "capability_tags": [
        "opencv.adaptive-threshold",
        "vision.filter"
      ],
      "runtime_requirements": {
        "python_packages": [
          "opencv-python",
          "numpy"
        ]
      },
      "node_pack_id": "opencv.basic-nodes",
      "node_pack_version": "0.1.0",
      "metadata": {}
    },
    {
      "format_id": "amvision.node-definition.v1",
      "node_type_id": "custom.opencv.binary-threshold",
      "display_name": "Binary Threshold",
      "category": "opencv.filter",
      "description": "把输入图片转为灰度后执行二值化。",
      "implementation_kind": "custom-node",
      "runtime_kind": "python-callable",
      "input_ports": [
        {
          "name": "image",
          "display_name": "Image",
          "payload_type_id": "image-ref.v1",
          "description": "",
          "required": true,
          "multiple": false,
          "metadata": {}
        }
      ],
      "output_ports": [
        {
          "name": "image",
          "display_name": "Image",
          "payload_type_id": "image-ref.v1",
          "description": "",
          "required": true,
          "multiple": false,
          "metadata": {}
        }
      ],
      "parameter_schema": {
        "type": "object",
        "properties": {
          "threshold": {
            "type": "number",
            "minimum": 0,
            "maximum": 255
          },
          "max_value": {
            "type": "number",
            "minimum": 0,
            "maximum": 255
          },
          "output_object_key": {
            "type": "string"
          }
        }
      },
      "parameter_ui_schema": null,
      "capability_tags": [
        "opencv.threshold",
        "vision.filter"
      ],
      "runtime_requirements": {
        "python_packages": [
          "opencv-python",
          "numpy"
        ]
      },
      "node_pack_id": "opencv.basic-nodes",
      "node_pack_version": "0.1.0",
      "metadata": {}
    },
    {
      "format_id": "amvision.node-definition.v1",
      "node_type_id": "custom.opencv.canny",
      "display_name": "Canny Edge",
      "category": "opencv.filter",
      "description": "对输入图片执行 Canny 边缘检测。",
      "implementation_kind": "custom-node",
      "runtime_kind": "python-callable",
      "input_ports": [
        {
          "name": "image",
          "display_name": "Image",
          "payload_type_id": "image-ref.v1",
          "description": "",
          "required": true,
          "multiple": false,
          "metadata": {}
        }
      ],
      "output_ports": [
        {
          "name": "image",
          "display_name": "Image",
          "payload_type_id": "image-ref.v1",
          "description": "",
          "required": true,
          "multiple": false,
          "metadata": {}
        }
      ],
      "parameter_schema": {
        "type": "object",
        "properties": {
          "threshold1": {
            "type": "number",
            "minimum": 0,
            "maximum": 255
          },
          "threshold2": {
            "type": "number",
            "minimum": 0,
            "maximum": 255
          },
          "aperture_size": {
            "type": "integer",
            "minimum": 3,
            "maximum": 7
          },
          "l2_gradient": {
            "type": "boolean"
          },
          "output_object_key": {
            "type": "string"
          }
        }
      },
      "parameter_ui_schema": null,
      "capability_tags": [
        "opencv.canny",
        "vision.filter"
      ],
      "runtime_requirements": {
        "python_packages": [
          "opencv-python",
          "numpy"
        ]
      },
      "node_pack_id": "opencv.basic-nodes",
      "node_pack_version": "0.1.0",
      "metadata": {}
    },
    {
      "format_id": "amvision.node-definition.v1",
      "node_type_id": "custom.opencv.connected-components",
      "display_name": "Connected Components",
      "category": "opencv.analysis",
      "description": "把二值前景图分解成连通区域，并输出标准 regions.v1 与摘要。",
      "implementation_kind": "custom-node",
      "runtime_kind": "python-callable",
      "input_ports": [
        {
          "name": "image",
          "display_name": "Image",
          "payload_type_id": "image-ref.v1",
          "description": "",
          "required": true,
          "multiple": false,
          "metadata": {}
        },
        {
          "name": "source_image",
          "display_name": "Source Image",
          "payload_type_id": "image-ref.v1",
          "description": "",
          "required": false,
          "multiple": false,
          "metadata": {}
        }
      ],
      "output_ports": [
        {
          "name": "regions",
          "display_name": "Regions",
          "payload_type_id": "regions.v1",
          "description": "",
          "required": true,
          "multiple": false,
          "metadata": {}
        },
        {
          "name": "summary",
          "display_name": "Summary",
          "payload_type_id": "value.v1",
          "description": "",
          "required": true,
          "multiple": false,
          "metadata": {}
        }
      ],
      "parameter_schema": {
        "type": "object",
        "properties": {
          "foreground_threshold": {
            "type": "integer",
            "minimum": 0,
            "maximum": 255
          },
          "connectivity": {
            "type": "integer",
            "enum": [
              4,
              8
            ]
          },
          "min_area": {
            "type": "number",
            "minimum": 0
          },
          "max_area": {
            "type": "number",
            "minimum": 0
          },
          "max_components": {
            "type": "integer",
            "minimum": 1
          },
          "region_id_prefix": {
            "type": "string",
            "default": "cc"
          },
          "class_id_default": {
            "type": "integer",
            "default": -1
          },
          "class_name_default": {
            "type": "string",
            "default": "component"
          },
          "score_default": {
            "type": "number",
            "minimum": 0,
            "default": 1.0
          }
        }
      },
      "parameter_ui_schema": null,
      "capability_tags": [
        "opencv.connected-components",
        "vision.analysis",
        "vision.region",
        "vision.diff"
      ],
      "runtime_requirements": {
        "python_packages": [
          "opencv-python",
          "numpy"
        ]
      },
      "node_pack_id": "opencv.basic-nodes",
      "node_pack_version": "0.1.0",
      "metadata": {}
    },
    {
      "format_id": "amvision.node-definition.v1",
      "node_type_id": "custom.opencv.contour",
      "display_name": "Contour",
      "category": "opencv.analysis",
      "description": "对输入图片提取 contour，并输出结构化 contour 集合。",
      "implementation_kind": "custom-node",
      "runtime_kind": "python-callable",
      "input_ports": [
        {
          "name": "image",
          "display_name": "Image",
          "payload_type_id": "image-ref.v1",
          "description": "",
          "required": true,
          "multiple": false,
          "metadata": {}
        }
      ],
      "output_ports": [
        {
          "name": "contours",
          "display_name": "Contours",
          "payload_type_id": "contours.v1",
          "description": "",
          "required": true,
          "multiple": false,
          "metadata": {}
        }
      ],
      "parameter_schema": {
        "type": "object",
        "properties": {
          "threshold": {
            "type": "integer",
            "minimum": 0,
            "maximum": 255
          },
          "retrieval_mode": {
            "type": "string",
            "enum": [
              "external",
              "list",
              "tree",
              "ccomp"
            ]
          },
          "approximation": {
            "type": "string",
            "enum": [
              "simple",
              "none",
              "tc89-l1",
              "tc89-kcos"
            ]
          },
          "min_area": {
            "type": "number",
            "minimum": 0
          },
          "max_contours": {
            "type": "integer",
            "minimum": 1
          }
        }
      },
      "parameter_ui_schema": null,
      "capability_tags": [
        "opencv.contour",
        "vision.analysis"
      ],
      "runtime_requirements": {
        "python_packages": [
          "opencv-python",
          "numpy"
        ]
      },
      "node_pack_id": "opencv.basic-nodes",
      "node_pack_version": "0.1.0",
      "metadata": {}
    },
    {
      "format_id": "amvision.node-definition.v1",
      "node_type_id": "custom.opencv.contour-filter",
      "display_name": "Contour Filter",
      "category": "opencv.analysis",
      "description": "按面积、宽高、点数和排序规则筛选 contour 集合。",
      "implementation_kind": "custom-node",
      "runtime_kind": "python-callable",
      "input_ports": [
        {
          "name": "contours",
          "display_name": "Contours",
          "payload_type_id": "contours.v1",
          "description": "",
          "required": true,
          "multiple": false,
          "metadata": {}
        }
      ],
      "output_ports": [
        {
          "name": "contours",
          "display_name": "Contours",
          "payload_type_id": "contours.v1",
          "description": "",
          "required": true,
          "multiple": false,
          "metadata": {}
        },
        {
          "name": "summary",
          "display_name": "Summary",
          "payload_type_id": "value.v1",
          "description": "",
          "required": true,
          "multiple": false,
          "metadata": {}
        }
      ],
      "parameter_schema": {
        "type": "object",
        "properties": {
          "min_area": {
            "type": "number",
            "minimum": 0
          },
          "max_area": {
            "type": "number",
            "minimum": 0
          },
          "min_width": {
            "type": "number",
            "minimum": 0
          },
          "max_width": {
            "type": "number",
            "minimum": 0
          },
          "min_height": {
            "type": "number",
            "minimum": 0
          },
          "max_height": {
            "type": "number",
            "minimum": 0
          },
          "min_point_count": {
            "type": "integer",
            "minimum": 0
          },
          "max_point_count": {
            "type": "integer",
            "minimum": 0
          },
          "sort_by": {
            "type": "string",
            "enum": [
              "contour_index",
              "point_count",
              "area",
              "width",
              "height",
              "perimeter"
            ]
          },
          "descending": {
            "type": "boolean"
          },
          "limit": {
            "type": "integer",
            "minimum": 1
          }
        }
      },
      "parameter_ui_schema": null,
      "capability_tags": [
        "opencv.contour-filter",
        "vision.analysis"
      ],
      "runtime_requirements": {
        "python_packages": [
          "opencv-python",
          "numpy"
        ]
      },
      "node_pack_id": "opencv.basic-nodes",
      "node_pack_version": "0.1.0",
      "metadata": {}
    },
    {
      "format_id": "amvision.node-definition.v1",
      "node_type_id": "custom.opencv.contours-to-regions",
      "display_name": "Contours To Regions",
      "category": "opencv.transform",
      "description": "把 contours.v1 规整成标准 regions.v1，便于继续接工业规则和 ROI/连续性节点。",
      "implementation_kind": "custom-node",
      "runtime_kind": "python-callable",
      "input_ports": [
        {
          "name": "contours",
          "display_name": "Contours",
          "payload_type_id": "contours.v1",
          "description": "",
          "required": true,
          "multiple": false,
          "metadata": {}
        },
        {
          "name": "image",
          "display_name": "Image",
          "payload_type_id": "image-ref.v1",
          "description": "",
          "required": false,
          "multiple": false,
          "metadata": {}
        }
      ],
      "output_ports": [
        {
          "name": "regions",
          "display_name": "Regions",
          "payload_type_id": "regions.v1",
          "description": "",
          "required": true,
          "multiple": false,
          "metadata": {}
        },
        {
          "name": "summary",
          "display_name": "Summary",
          "payload_type_id": "value.v1",
          "description": "",
          "required": true,
          "multiple": false,
          "metadata": {}
        }
      ],
      "parameter_schema": {
        "type": "object",
        "properties": {
          "region_id_prefix": {
            "type": "string",
            "default": "ctr"
          },
          "class_id_default": {
            "type": "integer",
            "default": -1
          },
          "class_name_default": {
            "type": "string",
            "default": "contour"
          },
          "score_default": {
            "type": "number",
            "minimum": 0,
            "default": 1.0
          }
        }
      },
      "parameter_ui_schema": null,
      "capability_tags": [
        "opencv.contours-to-regions",
        "vision.region",
        "vision.bridge"
      ],
      "runtime_requirements": {
        "python_packages": [
          "opencv-python",
          "numpy"
        ]
      },
      "node_pack_id": "opencv.basic-nodes",
      "node_pack_version": "0.1.0",
      "metadata": {}
    },
    {
      "format_id": "amvision.node-definition.v1",
      "node_type_id": "custom.opencv.crop-export",
      "display_name": "Crop Export",
      "category": "opencv.io",
      "description": "把 image 和 detections 裁成 image-refs.v1 图片集合。常见接法：原图接 image，检测结果接 detections，输出 crops 可继续接 Gallery Preview.images、Get Image Ref.images 或 QR Crop Decode Remap.crops。",
      "implementation_kind": "custom-node",
      "runtime_kind": "python-callable",
      "input_ports": [
        {
          "name": "image",
          "display_name": "Image",
          "payload_type_id": "image-ref.v1",
          "description": "待裁剪的原图。",
          "required": true,
          "multiple": false,
          "metadata": {
            "i18n": {
              "display_name": {
                "zh-CN": "原图",
                "en-US": "Image"
              },
              "description": {
                "zh-CN": "待裁剪的原图。",
                "en-US": "Source image used for crop extraction."
              }
            }
          }
        },
        {
          "name": "detections",
          "display_name": "Detections",
          "payload_type_id": "detections.v1",
          "description": "用于裁剪的 detections.v1 检测框集合。",
          "required": true,
          "multiple": false,
          "metadata": {
            "i18n": {
              "display_name": {
                "zh-CN": "检测结果",
                "en-US": "Detections"
              },
              "description": {
                "zh-CN": "用于裁剪的 detections.v1 检测框集合。",
                "en-US": "detections.v1 payload that provides the crop boxes."
              }
            }
          }
        }
      ],
      "output_ports": [
        {
          "name": "crops",
          "display_name": "Crops",
          "payload_type_id": "image-refs.v1",
          "description": "裁剪完成后的 image-refs.v1 图片集合。",
          "required": true,
          "multiple": false,
          "metadata": {
            "i18n": {
              "display_name": {
                "zh-CN": "裁剪图集",
                "en-US": "Crops"
              },
              "description": {
                "zh-CN": "裁剪完成后的 image-refs.v1 图片集合。",
                "en-US": "image-refs.v1 collection that contains the exported crops."
              }
            }
          }
        }
      ],
      "parameter_schema": {
        "type": "object",
        "properties": {
          "box_padding": {
            "type": "integer",
            "minimum": 0,
            "default": 0,
            "title": "Box padding",
            "description": "Expand every detection box by this many pixels before cropping.",
            "x-amvision-i18n": {
              "title": {
                "zh-CN": "边框扩展",
                "en-US": "Box padding"
              },
              "description": {
                "zh-CN": "裁剪前向四周额外扩展的像素数。",
                "en-US": "Number of pixels added around each detection box before cropping."
              }
            }
          },
          "max_crops": {
            "type": "integer",
            "minimum": 1,
            "title": "Max crops",
            "description": "Maximum number of crops to export. Leave empty to export all detections.",
            "x-amvision-i18n": {
              "title": {
                "zh-CN": "最大裁剪数",
                "en-US": "Max crops"
              },
              "description": {
                "zh-CN": "最多导出多少张裁剪图；留空时导出全部检测结果。",
                "en-US": "Maximum number of crops to export. Leave blank to export every detection."
              }
            }
          },
          "output_dir": {
            "type": "string",
            "title": "Output directory",
            "description": "Optional storage directory for exported crops. Leave empty to return memory image refs.",
            "x-amvision-i18n": {
              "title": {
                "zh-CN": "输出目录",
                "en-US": "Output directory"
              },
              "description": {
                "zh-CN": "可选输出目录；留空时返回 memory image-ref。",
                "en-US": "Optional storage directory for exported crops. Leave blank to return memory image refs."
              }
            }
          }
        }
      },
      "parameter_ui_schema": null,
      "capability_tags": [
        "opencv.crop",
        "vision.export"
      ],
      "runtime_requirements": {
        "python_packages": [
          "opencv-python",
          "numpy"
        ]
      },
      "node_pack_id": "opencv.basic-nodes",
      "node_pack_version": "0.1.0",
      "metadata": {
        "i18n": {
          "display_name": {
            "zh-CN": "裁剪导出",
            "en-US": "Crop Export"
          },
          "description": {
            "zh-CN": "把 image 和 detections 裁成 image-refs.v1 图片集合。常见接法：原图接 image，检测结果接 detections，输出 crops 可继续接 Gallery Preview.images、Get Image Ref.images 或 QR Crop Decode Remap.crops。",
            "en-US": "Crop the source image with detection boxes and output an image-refs.v1 collection. Typical wiring: source image -> image, detections -> detections, then connect crops to Gallery Preview.images, Get Image Ref.images, or QR Crop Decode Remap.crops."
          }
        }
      }
    },
    {
      "format_id": "amvision.node-definition.v1",
      "node_type_id": "custom.opencv.draw-detections",
      "display_name": "Draw Detections",
      "category": "opencv.render",
      "description": "通过 OpenCV 把 detection 结果绘制到图片上。",
      "implementation_kind": "custom-node",
      "runtime_kind": "python-callable",
      "input_ports": [
        {
          "name": "image",
          "display_name": "Image",
          "payload_type_id": "image-ref.v1",
          "description": "待绘制 detection 的原图。",
          "required": true,
          "multiple": false,
          "metadata": {
            "i18n": {
              "display_name": {
                "zh-CN": "原图",
                "en-US": "Image"
              },
              "description": {
                "zh-CN": "待绘制 detection 的原图。",
                "en-US": "Source image that receives the detection overlay."
              }
            }
          }
        },
        {
          "name": "detections",
          "display_name": "Detections",
          "payload_type_id": "detections.v1",
          "description": "标准 detections.v1 检测结果。",
          "required": true,
          "multiple": false,
          "metadata": {
            "i18n": {
              "display_name": {
                "zh-CN": "检测结果",
                "en-US": "Detections"
              },
              "description": {
                "zh-CN": "标准 detections.v1 检测结果。",
                "en-US": "Standard detections.v1 payload to render on the image."
              }
            }
          }
        }
      ],
      "output_ports": [
        {
          "name": "image",
          "display_name": "Image",
          "payload_type_id": "image-ref.v1",
          "description": "绘制完成后的输出图片。",
          "required": true,
          "multiple": false,
          "metadata": {
            "i18n": {
              "display_name": {
                "zh-CN": "输出图片",
                "en-US": "Image"
              },
              "description": {
                "zh-CN": "绘制完成后的输出图片。",
                "en-US": "Rendered output image with boxes and labels."
              }
            }
          }
        }
      ],
      "parameter_schema": {
        "type": "object",
        "properties": {
          "line_thickness": {
            "type": "integer",
            "minimum": 1,
            "default": 2,
            "description": "绘制 bbox 边框时使用的线宽。",
            "x-amvision-i18n": {
              "title": {
                "zh-CN": "线宽",
                "en-US": "Line thickness"
              },
              "description": {
                "zh-CN": "绘制 bbox 边框时使用的线宽。",
                "en-US": "Stroke width used for detection boxes."
              }
            }
          },
          "font_scale": {
            "type": "number",
            "minimum": 0,
            "default": 0.5,
            "description": "绘制标签文本时使用的字体缩放。",
            "x-amvision-i18n": {
              "title": {
                "zh-CN": "字体缩放",
                "en-US": "Font scale"
              },
              "description": {
                "zh-CN": "绘制标签文本时使用的字体缩放。",
                "en-US": "Font scale used when drawing labels."
              }
            }
          },
          "draw_scores": {
            "type": "boolean",
            "default": true,
            "description": "是否把 score 一起画到标签文本中。",
            "x-amvision-i18n": {
              "title": {
                "zh-CN": "绘制 score",
                "en-US": "Draw scores"
              },
              "description": {
                "zh-CN": "是否把 score 一起画到标签文本中。",
                "en-US": "Whether to include detection scores in the label text."
              }
            }
          },
          "output_object_key": {
            "type": "string",
            "description": "可选输出 object key；留空时返回 memory image-ref。",
            "x-amvision-i18n": {
              "title": {
                "zh-CN": "输出 object key",
                "en-US": "Output object key"
              },
              "description": {
                "zh-CN": "可选输出 object key；留空时返回 memory image-ref。",
                "en-US": "Optional output object key. When omitted, the node returns a memory image-ref."
              }
            }
          }
        }
      },
      "parameter_ui_schema": null,
      "capability_tags": [
        "opencv.draw",
        "vision.render"
      ],
      "runtime_requirements": {
        "python_packages": [
          "opencv-python",
          "numpy"
        ]
      },
      "node_pack_id": "opencv.basic-nodes",
      "node_pack_version": "0.1.0",
      "metadata": {
        "i18n": {
          "display_name": {
            "zh-CN": "绘制检测框",
            "en-US": "Draw Detections"
          },
          "description": {
            "zh-CN": "通过 OpenCV 把 detection 结果绘制到图片上。",
            "en-US": "Draw detection boxes and labels on the image with OpenCV."
          }
        }
      }
    },
    {
      "format_id": "amvision.node-definition.v1",
      "node_type_id": "custom.opencv.gallery-preview",
      "display_name": "Gallery Preview",
      "category": "opencv.preview",
      "description": "把 image-refs.v1 图片集合转换成可直接进入 HTTP 响应的 gallery body。最常见接法是直接连接 crop-export.crops，先快速检查每张裁剪图是否正确。",
      "implementation_kind": "custom-node",
      "runtime_kind": "python-callable",
      "input_ports": [
        {
          "name": "images",
          "display_name": "Images",
          "payload_type_id": "image-refs.v1",
          "description": "",
          "required": true,
          "multiple": false,
          "metadata": {}
        }
      ],
      "output_ports": [
        {
          "name": "body",
          "display_name": "Body",
          "payload_type_id": "response-body.v1",
          "description": "",
          "required": true,
          "multiple": false,
          "metadata": {}
        }
      ],
      "parameter_schema": {
        "type": "object",
        "properties": {
          "title": {
            "type": "string"
          },
          "max_items": {
            "type": "integer",
            "minimum": 1
          },
          "response_transport_mode": {
            "type": "string",
            "enum": [
              "inline-base64",
              "storage-ref"
            ]
          },
          "output_dir": {
            "type": "string"
          }
        }
      },
      "parameter_ui_schema": null,
      "capability_tags": [
        "ui.gallery",
        "response.body"
      ],
      "runtime_requirements": {},
      "node_pack_id": "opencv.basic-nodes",
      "node_pack_version": "0.1.0",
      "metadata": {
        "i18n": {
          "description": {
            "zh-CN": "把 image-refs.v1 图片集合转换成可直接进入 HTTP 响应的 gallery body。最常见接法是直接连接 crop-export.crops，先快速检查每张裁剪图是否正确。",
            "en-US": "Convert an image-refs.v1 collection into a gallery response body. The most common wiring is crop-export.crops -> images so the cropped images can be inspected quickly."
          }
        }
      }
    },
    {
      "format_id": "amvision.node-definition.v1",
      "node_type_id": "custom.opencv.gaussian-blur",
      "display_name": "Gaussian Blur",
      "category": "opencv.filter",
      "description": "对输入图片执行高斯模糊。",
      "implementation_kind": "custom-node",
      "runtime_kind": "python-callable",
      "input_ports": [
        {
          "name": "image",
          "display_name": "Image",
          "payload_type_id": "image-ref.v1",
          "description": "",
          "required": true,
          "multiple": false,
          "metadata": {}
        }
      ],
      "output_ports": [
        {
          "name": "image",
          "display_name": "Image",
          "payload_type_id": "image-ref.v1",
          "description": "",
          "required": true,
          "multiple": false,
          "metadata": {}
        }
      ],
      "parameter_schema": {
        "type": "object",
        "properties": {
          "kernel_size": {
            "type": "integer",
            "minimum": 1
          },
          "sigma_x": {
            "type": "number",
            "minimum": 0
          },
          "output_object_key": {
            "type": "string"
          }
        }
      },
      "parameter_ui_schema": null,
      "capability_tags": [
        "opencv.blur",
        "vision.filter"
      ],
      "runtime_requirements": {
        "python_packages": [
          "opencv-python",
          "numpy"
        ]
      },
      "node_pack_id": "opencv.basic-nodes",
      "node_pack_version": "0.1.0",
      "metadata": {}
    },
    {
      "format_id": "amvision.node-definition.v1",
      "node_type_id": "custom.opencv.grayscale",
      "display_name": "Grayscale",
      "category": "opencv.filter",
      "description": "把输入图片转为灰度图。",
      "implementation_kind": "custom-node",
      "runtime_kind": "python-callable",
      "input_ports": [
        {
          "name": "image",
          "display_name": "Image",
          "payload_type_id": "image-ref.v1",
          "description": "",
          "required": true,
          "multiple": false,
          "metadata": {}
        }
      ],
      "output_ports": [
        {
          "name": "image",
          "display_name": "Image",
          "payload_type_id": "image-ref.v1",
          "description": "",
          "required": true,
          "multiple": false,
          "metadata": {}
        }
      ],
      "parameter_schema": {
        "type": "object",
        "properties": {
          "output_object_key": {
            "type": "string"
          }
        }
      },
      "parameter_ui_schema": null,
      "capability_tags": [
        "opencv.grayscale",
        "vision.filter"
      ],
      "runtime_requirements": {
        "python_packages": [
          "opencv-python",
          "numpy"
        ]
      },
      "node_pack_id": "opencv.basic-nodes",
      "node_pack_version": "0.1.0",
      "metadata": {}
    },
    {
      "format_id": "amvision.node-definition.v1",
      "node_type_id": "custom.opencv.image-diff",
      "display_name": "Image Diff",
      "category": "opencv.analysis",
      "description": "对当前图片和参考图片执行绝对差分，生成差异图和差异摘要。",
      "implementation_kind": "custom-node",
      "runtime_kind": "python-callable",
      "input_ports": [
        {
          "name": "image",
          "display_name": "Image",
          "payload_type_id": "image-ref.v1",
          "description": "",
          "required": true,
          "multiple": false,
          "metadata": {}
        },
        {
          "name": "reference_image",
          "display_name": "Reference Image",
          "payload_type_id": "image-ref.v1",
          "description": "",
          "required": true,
          "multiple": false,
          "metadata": {}
        }
      ],
      "output_ports": [
        {
          "name": "image",
          "display_name": "Image",
          "payload_type_id": "image-ref.v1",
          "description": "",
          "required": true,
          "multiple": false,
          "metadata": {}
        },
        {
          "name": "summary",
          "display_name": "Summary",
          "payload_type_id": "value.v1",
          "description": "",
          "required": true,
          "multiple": false,
          "metadata": {}
        }
      ],
      "parameter_schema": {
        "type": "object",
        "properties": {
          "diff_mode": {
            "type": "string",
            "enum": [
              "grayscale",
              "color"
            ]
          },
          "output_object_key": {
            "type": "string"
          }
        }
      },
      "parameter_ui_schema": null,
      "capability_tags": [
        "opencv.image-diff",
        "vision.analysis",
        "vision.diff"
      ],
      "runtime_requirements": {
        "python_packages": [
          "opencv-python",
          "numpy"
        ]
      },
      "node_pack_id": "opencv.basic-nodes",
      "node_pack_version": "0.1.0",
      "metadata": {}
    },
    {
      "format_id": "amvision.node-definition.v1",
      "node_type_id": "custom.opencv.measure",
      "display_name": "Measure",
      "category": "opencv.analysis",
      "description": "对 contour 集合执行面积、周长与包围框度量。",
      "implementation_kind": "custom-node",
      "runtime_kind": "python-callable",
      "input_ports": [
        {
          "name": "contours",
          "display_name": "Contours",
          "payload_type_id": "contours.v1",
          "description": "",
          "required": true,
          "multiple": false,
          "metadata": {}
        }
      ],
      "output_ports": [
        {
          "name": "measurements",
          "display_name": "Measurements",
          "payload_type_id": "measurements.v1",
          "description": "",
          "required": true,
          "multiple": false,
          "metadata": {}
        }
      ],
      "parameter_schema": {
        "type": "object",
        "properties": {
          "sort_by": {
            "type": "string",
            "enum": [
              "contour_index",
              "area",
              "perimeter",
              "width",
              "height"
            ]
          },
          "descending": {
            "type": "boolean"
          },
          "limit": {
            "type": "integer",
            "minimum": 1
          }
        }
      },
      "parameter_ui_schema": null,
      "capability_tags": [
        "opencv.measure",
        "vision.analysis"
      ],
      "runtime_requirements": {
        "python_packages": [
          "opencv-python",
          "numpy"
        ]
      },
      "node_pack_id": "opencv.basic-nodes",
      "node_pack_version": "0.1.0",
      "metadata": {}
    },
    {
      "format_id": "amvision.node-definition.v1",
      "node_type_id": "custom.opencv.min-area-rect",
      "display_name": "Min Area Rect",
      "category": "opencv.analysis",
      "description": "对 contour 集合计算最小外接旋转矩形，并输出结构化 rotated-rects.v1。",
      "implementation_kind": "custom-node",
      "runtime_kind": "python-callable",
      "input_ports": [
        {
          "name": "contours",
          "display_name": "Contours",
          "payload_type_id": "contours.v1",
          "description": "",
          "required": true,
          "multiple": false,
          "metadata": {}
        }
      ],
      "output_ports": [
        {
          "name": "rotated_rects",
          "display_name": "Rotated Rects",
          "payload_type_id": "rotated-rects.v1",
          "description": "",
          "required": true,
          "multiple": false,
          "metadata": {}
        },
        {
          "name": "summary",
          "display_name": "Summary",
          "payload_type_id": "value.v1",
          "description": "",
          "required": true,
          "multiple": false,
          "metadata": {}
        }
      ],
      "parameter_schema": {
        "type": "object",
        "properties": {
          "sort_by": {
            "type": "string",
            "enum": [
              "contour_index",
              "contour_area",
              "rect_area",
              "long_side",
              "short_side",
              "angle_deg",
              "fill_ratio"
            ]
          },
          "descending": {
            "type": "boolean"
          },
          "limit": {
            "type": "integer",
            "minimum": 1
          }
        }
      },
      "parameter_ui_schema": null,
      "capability_tags": [
        "opencv.min-area-rect",
        "vision.geometry",
        "vision.analysis"
      ],
      "runtime_requirements": {
        "python_packages": [
          "opencv-python",
          "numpy"
        ]
      },
      "node_pack_id": "opencv.basic-nodes",
      "node_pack_version": "0.1.0",
      "metadata": {}
    },
    {
      "format_id": "amvision.node-definition.v1",
      "node_type_id": "custom.opencv.morphology",
      "display_name": "Morphology",
      "category": "opencv.filter",
      "description": "对输入图片执行 morphology 操作。",
      "implementation_kind": "custom-node",
      "runtime_kind": "python-callable",
      "input_ports": [
        {
          "name": "image",
          "display_name": "Image",
          "payload_type_id": "image-ref.v1",
          "description": "",
          "required": true,
          "multiple": false,
          "metadata": {}
        }
      ],
      "output_ports": [
        {
          "name": "image",
          "display_name": "Image",
          "payload_type_id": "image-ref.v1",
          "description": "",
          "required": true,
          "multiple": false,
          "metadata": {}
        }
      ],
      "parameter_schema": {
        "type": "object",
        "properties": {
          "operation": {
            "type": "string",
            "enum": [
              "erode",
              "dilate",
              "open",
              "close",
              "gradient",
              "top-hat",
              "black-hat"
            ]
          },
          "shape": {
            "type": "string",
            "enum": [
              "rect",
              "ellipse",
              "cross"
            ]
          },
          "kernel_size": {
            "type": "integer",
            "minimum": 1
          },
          "iterations": {
            "type": "integer",
            "minimum": 1
          },
          "output_object_key": {
            "type": "string"
          }
        }
      },
      "parameter_ui_schema": null,
      "capability_tags": [
        "opencv.morphology",
        "vision.filter"
      ],
      "runtime_requirements": {
        "python_packages": [
          "opencv-python",
          "numpy"
        ]
      },
      "node_pack_id": "opencv.basic-nodes",
      "node_pack_version": "0.1.0",
      "metadata": {}
    },
    {
      "format_id": "amvision.node-definition.v1",
      "node_type_id": "custom.opencv.otsu-threshold",
      "display_name": "Otsu Threshold",
      "category": "opencv.filter",
      "description": "对输入灰度图执行 Otsu 自动阈值分割。",
      "implementation_kind": "custom-node",
      "runtime_kind": "python-callable",
      "input_ports": [
        {
          "name": "image",
          "display_name": "Image",
          "payload_type_id": "image-ref.v1",
          "description": "",
          "required": true,
          "multiple": false,
          "metadata": {}
        }
      ],
      "output_ports": [
        {
          "name": "image",
          "display_name": "Image",
          "payload_type_id": "image-ref.v1",
          "description": "",
          "required": true,
          "multiple": false,
          "metadata": {}
        }
      ],
      "parameter_schema": {
        "type": "object",
        "properties": {
          "max_value": {
            "type": "number",
            "minimum": 0,
            "maximum": 255
          },
          "threshold_type": {
            "type": "string",
            "enum": [
              "binary",
              "binary-inv"
            ]
          },
          "output_object_key": {
            "type": "string"
          }
        }
      },
      "parameter_ui_schema": null,
      "capability_tags": [
        "opencv.otsu-threshold",
        "vision.filter"
      ],
      "runtime_requirements": {
        "python_packages": [
          "opencv-python",
          "numpy"
        ]
      },
      "node_pack_id": "opencv.basic-nodes",
      "node_pack_version": "0.1.0",
      "metadata": {}
    },
    {
      "format_id": "amvision.node-definition.v1",
      "node_type_id": "custom.opencv.payload-to-value",
      "display_name": "OpenCV Payload To Value",
      "category": "opencv.transform",
      "description": "把 contours.v1、measurements.v1 或 rotated-rects.v1 包装成 value.v1，供 object-create、response-envelope 和 value-preview 继续组合或预览。",
      "implementation_kind": "custom-node",
      "runtime_kind": "python-callable",
      "input_ports": [
        {
          "name": "contours",
          "display_name": "Contours",
          "payload_type_id": "contours.v1",
          "description": "待包装的 contour 结果。",
          "required": false,
          "multiple": false,
          "metadata": {
            "i18n": {
              "display_name": {
                "zh-CN": "轮廓结果",
                "en-US": "Contours"
              },
              "description": {
                "zh-CN": "待包装的 contour 结果。",
                "en-US": "Contour result to wrap as value.v1."
              }
            }
          }
        },
        {
          "name": "measurements",
          "display_name": "Measurements",
          "payload_type_id": "measurements.v1",
          "description": "待包装的 measurement 结果。",
          "required": false,
          "multiple": false,
          "metadata": {
            "i18n": {
              "display_name": {
                "zh-CN": "测量结果",
                "en-US": "Measurements"
              },
              "description": {
                "zh-CN": "待包装的 measurement 结果。",
                "en-US": "Measurement result to wrap as value.v1."
              }
            }
          }
        },
        {
          "name": "rotated_rects",
          "display_name": "Rotated Rects",
          "payload_type_id": "rotated-rects.v1",
          "description": "待包装的 rotated-rects 结果。",
          "required": false,
          "multiple": false,
          "metadata": {
            "i18n": {
              "display_name": {
                "zh-CN": "旋转矩形结果",
                "en-US": "Rotated Rects"
              },
              "description": {
                "zh-CN": "待包装的 rotated-rects 结果。",
                "en-US": "Rotated-rects result to wrap as value.v1."
              }
            }
          }
        }
      ],
      "output_ports": [
        {
          "name": "value",
          "display_name": "Value",
          "payload_type_id": "value.v1",
          "description": "可继续交给 Create Object、Response Envelope 或 Value Preview 的 value payload。",
          "required": true,
          "multiple": false,
          "metadata": {
            "i18n": {
              "display_name": {
                "zh-CN": "值",
                "en-US": "Value"
              },
              "description": {
                "zh-CN": "可继续交给 Create Object、Response Envelope 或 Value Preview 的 value payload。",
                "en-US": "value.v1 payload ready for Create Object, Response Envelope, or Value Preview."
              }
            }
          }
        }
      ],
      "parameter_schema": {
        "type": "object",
        "properties": {}
      },
      "parameter_ui_schema": null,
      "capability_tags": [
        "opencv.transform",
        "value.bridge"
      ],
      "runtime_requirements": {},
      "node_pack_id": "opencv.basic-nodes",
      "node_pack_version": "0.1.0",
      "metadata": {
        "i18n": {
          "display_name": {
            "zh-CN": "OpenCV 结果转值",
            "en-US": "OpenCV Payload To Value"
          },
          "description": {
            "zh-CN": "把 contours.v1、measurements.v1 或 rotated-rects.v1 包装成 value.v1，便于继续组合 JSON 响应或统一做 JSON 预览。",
            "en-US": "Wrap contours.v1, measurements.v1, or rotated-rects.v1 as value.v1 so the result can be composed into JSON responses or previewed as JSON."
          }
        }
      }
    },
    {
      "format_id": "amvision.node-definition.v1",
      "node_type_id": "custom.opencv.resize",
      "display_name": "Resize",
      "category": "opencv.filter",
      "description": "按目标宽高缩放输入图片；当仅提供一个边时按原始比例推导另一边。",
      "implementation_kind": "custom-node",
      "runtime_kind": "python-callable",
      "input_ports": [
        {
          "name": "image",
          "display_name": "Image",
          "payload_type_id": "image-ref.v1",
          "description": "",
          "required": true,
          "multiple": false,
          "metadata": {}
        }
      ],
      "output_ports": [
        {
          "name": "image",
          "display_name": "Image",
          "payload_type_id": "image-ref.v1",
          "description": "",
          "required": true,
          "multiple": false,
          "metadata": {}
        }
      ],
      "parameter_schema": {
        "type": "object",
        "properties": {
          "width": {
            "type": "integer",
            "minimum": 1
          },
          "height": {
            "type": "integer",
            "minimum": 1
          },
          "interpolation": {
            "type": "string",
            "enum": [
              "nearest",
              "linear",
              "area",
              "cubic",
              "lanczos4"
            ]
          },
          "output_object_key": {
            "type": "string"
          }
        }
      },
      "parameter_ui_schema": null,
      "capability_tags": [
        "opencv.resize",
        "vision.filter"
      ],
      "runtime_requirements": {
        "python_packages": [
          "opencv-python",
          "numpy"
        ]
      },
      "node_pack_id": "opencv.basic-nodes",
      "node_pack_version": "0.1.0",
      "metadata": {}
    }
  ],
  "metadata": {}
}
