{
  "format_id": "amvision.node-definition.v1",
  "node_type_id": "custom.barcode.all-linear-decode",
  "display_name": "Decode All Linear Barcodes",
  "category": "barcode.decode",
  "description": "扫描输入图片中的全部一维条码制式，适合物流、零售与工业通用线性码场景。",
  "implementation_kind": "custom-node",
  "runtime_kind": "python-callable",
  "input_ports": [
    {
      "name": "image",
      "display_name": "Image",
      "payload_type_id": "image-ref.v1"
    }
  ],
  "output_ports": [
    {
      "name": "results",
      "display_name": "Results",
      "payload_type_id": "barcode-results.v1"
    }
  ],
  "parameter_schema": {
    "type": "object",
    "properties": {
      "try_rotate": {
        "type": "boolean",
        "default": true,
        "description": "默认启用旋转尝试，适合大多数现场图片。"
      },
      "try_downscale": {
        "type": "boolean",
        "default": true,
        "description": "默认启用缩放尝试，便于识读大尺寸条码图。"
      },
      "try_invert": {
        "type": "boolean",
        "default": true,
        "description": "默认启用反色尝试，适合浅码深底或深码浅底混合场景。"
      },
      "is_pure": {
        "type": "boolean",
        "default": false,
        "description": "纯净条码图才建议开启；普通实拍图默认关闭。"
      },
      "return_errors": {
        "type": "boolean",
        "default": false,
        "description": "默认只返回成功结果；调试识读失败原因时再开启。"
      },
      "text_mode": {
        "type": "string",
        "default": "hri",
        "enum": [
          "plain",
          "hri",
          "escaped",
          "hex",
          "eci",
          "hex-eci"
        ],
        "description": "默认使用 hri，兼顾可读文本和常见条码显示习惯。"
      },
      "binarizer": {
        "type": "string",
        "default": "local-average",
        "enum": [
          "local-average",
          "global-histogram",
          "fixed-threshold",
          "bool-cast"
        ],
        "description": "默认使用 local-average，适合亮度不均的工业图像。"
      },
      "ean_add_on_symbol": {
        "type": "string",
        "default": "ignore",
        "enum": [
          "ignore",
          "read",
          "require"
        ],
        "description": "默认忽略 EAN add-on；只有明确需要副码时再切换。"
      }
    }
  },
  "capability_tags": [
    "barcode.decode",
    "barcode.all-linear"
  ],
  "runtime_requirements": {
    "python_packages": [
      "opencv-python",
      "numpy",
      "zxing-cpp"
    ]
  },
  "node_pack_id": "barcode.protocol-nodes",
  "node_pack_version": "0.1.0",
  "metadata": {
    "family": "linear",
    "variant": "all-linear",
    "scope_kind": "group",
    "format_member_name": "AllLinear"
  }
}
